MANIFEST.in
README.md
setup.py
django_poormanscron.egg-info/PKG-INFO
django_poormanscron.egg-info/SOURCES.txt
django_poormanscron.egg-info/dependency_links.txt
django_poormanscron.egg-info/not-zip-safe
django_poormanscron.egg-info/top_level.txt
poormanscron/__init__.py
poormanscron/admin.py
poormanscron/middleware.py
poormanscron/models.py
poormanscron/fixtures/__init__.py