Metadata-Version: 1.0
Name: django-poormanscron
Version: 0.1.3
Summary: Poor Man's Cron is Django app which makes use of spambots, search engine indexing robots and alike to run scheduled tasks in approximately regular intervals.
Home-page: https://github.com/BBB/django-poormanscron/tree/master/
Author: Bruno Renié & Ollie Relph
Author-email: aidas.bendoraitis@gmail.com & ollie@relph.me
License: BSD
Platform: UNKNOWN
